statprof.py
statprof_smarkets-0.2.0.dist-info/DESCRIPTION.rst
statprof_smarkets-0.2.0.dist-info/METADATA
statprof_smarkets-0.2.0.dist-info/RECORD
statprof_smarkets-0.2.0.dist-info/WHEEL
statprof_smarkets-0.2.0.dist-info/metadata.json
statprof_smarkets-0.2.0.dist-info/top_level.txt
