Metadata-Version: 2.0
Name: statprof-smarkets
Version: 0.2.0
Summary: Statistical profiling for Python
Home-page: https://github.com/smarkets/statprof
Author: Smarkets
Author-email: support@smarkets.com
License: LGPL 2, see LICENSE file
Keywords: profiling,statistical profiling,statprof
Platform: UNKNOWN
Classifier: Development Status :: 3 - Alpha
Classifier: Topic :: Utilities
Classifier: License :: OSI Approved :: GNU Library or Lesser General Public License (LGPL)
Classifier: Programming Language :: Python
Classifier: Programming Language :: Python :: 2
Classifier: Programming Language :: Python :: 3
Requires-Dist: six (>=1.5.0)
